README.md
pyproject.toml
modelstat/__init__.py
modelstat/core.py
modelstat/_utils/__init__.py
modelstat/_utils/typehinting.py
modelstat-0.1.0.dist-info/METADATA
modelstat-0.1.0.dist-info/WHEEL
modelstat-0.1.0.dist-info/RECORD
