Metadata-Version: 2.3
Name: modelstat
Version: 0.1.0
Summary: Your package description
Author-email: Your Name <your.email@example.com>
Requires-Python: >=3.11
Requires-Dist: numpy
